geneticml/__init__.py
geneticml/algorithms.py
geneticml/optimizers.py
geneticml/strategy.py
geneticml-1.0.8.dist-info/LICENSE
geneticml-1.0.8.dist-info/METADATA
geneticml-1.0.8.dist-info/WHEEL
geneticml-1.0.8.dist-info/top_level.txt
geneticml-1.0.8.dist-info/RECORD
