Metadata-Version: 2.1
Name: geneticml
Version: 1.0.8
Summary: A simple and lightweight genetic algorithm for optimization of any machine learning model
Home-page: https://github.com/albarsil/geneticml
Author: Allan Barcelos
Author-email: albarsil@gmail.com
License: MIT
Keywords: machine learning,genetic,sklearn,pytorch,data science
Platform: UNKNOWN
Classifier: License :: OSI Approved :: MIT License
Classifier: Programming Language :: Python :: 3.7
Classifier: Programming Language :: Python :: 3.8
Classifier: Programming Language :: Python :: 3.9
License-File: LICENSE
Requires-Dist: tqdm
